{
  "project_info": {
    "project_number": "257525546002",
    "project_id": "agua-935ed",
    "storage_bucket": "agua-935ed.appspot.com"
  },
  "client": [
    {
      "client_info": {
        "mobilesdk_app_id": "1:257525546002:android:cdfe650b70f4fe4e72accb",
        "android_client_info": {
          "package_name": "agua.flaviodeoliveira.com.agua"
        }
      },
      "oauth_client": [
        {
          "client_id": "257525546002-7051pu35661bqd0472n3eu51a41p9jma.apps.googleusercontent.com",
          "client_type": 3
        }
      ],
      "api_key": [
        {
          "current_key": "AIzaSyCLnLQh0AjnL1GcpKi24bHtNRuQgHN31q0"
        }
      ],
      "services": {
        "appinvite_service": {
          "other_platform_oauth_client": [
            {
              "client_id": "257525546002-7051pu35661bqd0472n3eu51a41p9jma.apps.googleusercontent.com",
              "client_type": 3
            }
          ]
        }
      }
    }
  ],
  "configuration_version": "1"
}